bizstats_vector_store/__init__.py
bizstats_vector_store/config.py
bizstats_vector_store/chunking/__init__.py
bizstats_vector_store/chunking/document.py
bizstats_vector_store/embedding/__init__.py
bizstats_vector_store/embedding/service.py
bizstats_vector_store/milvus/__init__.py
bizstats_vector_store/milvus/client.py
bizstats_vector_store/milvus/collections.py
bizstats_vector_store/models/__init__.py
bizstats_vector_store/models/enums.py
bizstats_vector_store/models/schemas.py
bizstats_vector_store/search/__init__.py
bizstats_vector_store/search/semantic.py
bizstats_vector_store-0.1.0.dist-info/METADATA
bizstats_vector_store-0.1.0.dist-info/WHEEL
bizstats_vector_store-0.1.0.dist-info/RECORD
