Metadata-Version: 2.4
Name: bizstats-vector-store
Version: 0.1.0
Summary: Milvus vector database wrapper with embedding generation and semantic search for BizStats applications
Project-URL: Homepage, https://bizstats.ai
Project-URL: Documentation, https://docs.bizstats.ai/packages/vector-store
Project-URL: Repository, https://bitbucket.org/absolut-e/smart-mcp
Author-email: "BizStats.AI" <account@absolut-e.com>
License: Proprietary
Keywords: embeddings,milvus,ollama,rag,semantic-search,vector-database
Classifier: Development Status :: 4 - Beta
Classifier: Intended Audience :: Developers
Classifier: License :: Other/Proprietary License
Classifier: Operating System :: OS Independent
Classifier: Programming Language :: Python :: 3
Classifier: Programming Language :: Python :: 3.11
Classifier: Programming Language :: Python :: 3.12
Classifier: Programming Language :: Python :: 3.13
Classifier: Topic :: Database
Classifier: Topic :: Scientific/Engineering :: Artificial Intelligence
Classifier: Topic :: Software Development :: Libraries :: Python Modules
Requires-Python: >=3.11
Requires-Dist: httpx>=0.25.0
Requires-Dist: pydantic-settings>=2.0.0
Requires-Dist: pydantic>=2.0.0
Requires-Dist: pymilvus>=2.3.0
Requires-Dist: redis>=5.0.0
Provides-Extra: all
Requires-Dist: ollama>=0.1.0; extra == 'all'
Requires-Dist: openai>=1.0.0; extra == 'all'
Provides-Extra: dev
Requires-Dist: black>=24.0.0; extra == 'dev'
Requires-Dist: mypy>=1.8.0; extra == 'dev'
Requires-Dist: pytest-asyncio>=0.23.0; extra == 'dev'
Requires-Dist: pytest-cov>=4.1.0; extra == 'dev'
Requires-Dist: pytest>=8.0.0; extra == 'dev'
Requires-Dist: ruff>=0.1.0; extra == 'dev'
Provides-Extra: ollama
Requires-Dist: ollama>=0.1.0; extra == 'ollama'
Provides-Extra: openai
Requires-Dist: openai>=1.0.0; extra == 'openai'
Provides-Extra: test
Requires-Dist: pytest-asyncio>=0.23.0; extra == 'test'
Requires-Dist: pytest-cov>=4.1.0; extra == 'test'
Requires-Dist: pytest-mock>=3.12.0; extra == 'test'
Requires-Dist: pytest>=8.0.0; extra == 'test'
